Workbook

Sheet Hoja1
A1: distribucion | B1: portal del sol | C1: cliente | D1: pancho | E1: haburguesa | F1: lactal blac | G1: lactal neg | H1: lomo | I1: pizza | J1: anis12 | K1: anis24 | L1: panchogrande6 | M1: alfajor glase | N1: alfajor miel | O1: alfajor maise | P1: alfajor de chocolat | Q1: pan dulce | R1: limon surtida 3kg | S1: naranja surtida 3kg | T1: coco surtida 3kg | U1: rosca glaciada | V1: Vainillas 2kg | W1: pepa 2,5kg | X1: surtida 2.5kg | Y1: surtidas 800g | Z1: surtidas 400g | AA1: miel 400g | AB1: Sandwich de miga grande | AC1: Sandwich de miga chico | AD1: pebete de jamon y queso | AE1: Sandwich miga salame gr | AF1: maisena | AG1: glaciado | AH1: miel | AJ1: conv/miel/mais | AK1: chocotorta | AL1: tiramisu | AM1: ensalda de fruta | AN1: gelatina | AP1: premium | AQ1: maisena | AR1: miel | AS1: glaciado | AT1: chocolate | AU1: combinado | AV1: alfajor frutal | AW1: miel 1kg | AX1: maisena 1kg | AY1: tartateleta cabsha
B2: 1 | C2: semana 1 (1/ 5---8/05) 2024)
B5: 1 | C5: alumine | AF5: 1 | AG5: 1
B6: 2 | C6: lisandro y balbin
B7: 3 | C7: moto
B8: 5
B9: 6
B10: 4 | C10: tejada
B11: 5 | C11: santa rosa ivana
B12: 7
B13: 8
B14: 6 | C14: riojay beltran
B16: 7 | C16: paso de los andesy cant
B17: 8 | C17: godoy 1884
B18: 9 | C18: bomba y 17 de oct
B19: 10 | C19: sguasini
B20: 11 | C20: teniete
B21: 12 | C21: negro
B22: 13 | C22: roca y sarmiento
B23: 14 | C23: roca 829
B24: 18
B25: 15 | C25: camargo
B26: 16 | C26: hugo
B27: 17 | C27: viejo almacen
B28: 22
B29: 23
B30: 18 | C30: serpa
B31: 19 | C31: villega
B32: 26
B33: 27
B34: 20 | C34: rico pan
B35: 29
B36: 21 | C36: sanguchito
B37: 22 | C37: yo
B38: 30
B39: 23 | C39: turco
B40: 24 | C40: avellaneda y rio
B42: 33
A46: =SUM(A3:A41) -> 0 | B46: total | C46: tot
D51: =SUM(D3:D50) -> 0 | E51: =SUM(E3:E50) -> 0 | F51: =SUM(F3:F50) -> 0 | G51: =SUM(G3:G50) -> 0 | H51: =SUM(H3:H50) -> 0 | I51: =SUM(I3:I50) -> 0 | J51: =SUM(J3:J50) -> 0 | K51: =SUM(K3:K50) -> 0 | ... AY51: =SUM(AY3:AY50) -> 0
B57: producto
B58: via canell | C58: cant total | D58: precios total | E58: costo | G58: ganancias | Y58: candela
B59: pancho | C59: =D51 -> 0 | D59: =S62*C59 -> 0 | E59: =T61*C59 -> 0 | M59: lauti | R59: via canel | U59: portal del sol | Y59: alfajores candela
B60: haburgue | C60: =E51 -> 0 | D60: =S61*C60 -> 0 | E60: =T62*C60 -> 0 | M60: _-Lista de Precios REVENTA Julio 2024-_ | S60: Precio | U60: Polvoron x 3kg | V60: =W60*1.303 -> 10293.7 | W60: 7900 | Y60: maisena | Z60: =AA60*1.318 -> 6853.6 | AA60: 5200
B61: lactal blan | C61: =F51 -> 0 | D61: =S64*C61 -> 0 | E61: =T63*C61 -> 0 | R61: HAMBURGUESA | S61: =T61*1.407 -> 914.55 | T61: 650 | U61: Surtido x2.5kg | V61: =W61*1.303 -> 9772.5 | W61: 7500 | Y61: miel | Z61: =AA61*1.318 -> 6853.6 | AA61: 5200
B62: lactal negr | C62: =G51 -> 0 | D62: =S64*C62 -> 0 | E62: =T64*C62 -> 0 | M62: *SANDWICHES* | R62: PANCHOS | S62: =T62*1.407 -> 914.55 | T62: 650 | U62: surtido 1.5kg | V62: =W62*1.303 -> 4560.5 | W62: 3500 | Y62: glaciado | Z62: =AA62*1.318 -> 6853.6 | AA62: 5200
B63: lomo | C63: =H51 -> 0 | D63: =S66*C63 -> 0 | E63: =T66*C63 -> 0 | M63: salguchi de miga grande salame | N63: =P63*1.43 -> 2145 | P63: 1500 | R63: LACTAL BLANCO | S63: =T63*1.479 -> 1267.503 | T63: 857 | U63: Surtido x 800gr | V63: =W63*1.303 -> 2736.3 | W63: 2100 | Y63: combinado | Z63: =AA63*1.32 -> 7260 | AA63: 5500
B64: pizza | C64: =I51 -> 0 | D64: =S65*C64 -> 0 | E64: =T65*C64 -> 0 | M64: Sandwich de miga grande | N64: =P64*1.42 -> 1988 | P64: 1400 | R64: LACTAL SALVADO | S64: =T64*1.479 -> 1267.503 | T64: 857 | U64: Surtido 14x400gr el pqt. | V64: =W64*1.303 -> 1274.334 | W64: 978 | Y64: cabsha | Z64: =AA64*1.32 -> 7260 | AA64: 5500
B65: aniz12 | C65: =J51 -> 0 | D65: =S70*C65 -> 0 | E65: =D128*C65 -> 0 | M65: Sandwich de miga chico | N65: =P65*1.4 -> 1540 | P65: 1100 | R65: PRE PIZZA | S65: =T65*1.3 -> 2113.8 | T65: 1626 | U65: biscochos de miel 400g | V65: =W65*1.303 -> 1469.784 | W65: 1128 | Y65: pastaflorea membrillo | Z65: =AA65*1.318 -> 6853.6 | AA65: 5200
B66: anis24 | C66: =K51 -> 0 | D66: =S71*C66 -> 0 | E66: =T71*C66 -> 0 | M66: Sandwich miga Triple PREMIUM | N66: =P66*1.4 -> 1890 | P66: 1350 | R66: pan arabe 4 uds | S66: =T66*1.436 -> 1711.712 | T66: 1192 | U66: Vainilla 20x 270gr el pqt. | V66: =W66*1.303 -> 8404.35 | W66: 6450 | Y66: maisena de kg | Z66: =AA66*1.32 -> 10560 | AA66: 8000
B67: super pacho de 6 | C67: =L51 -> 0 | D67: =S67*C67 -> 0 | E67: =T67*C67 -> 0 | F67: costo | M67: Sandwich miga Triple PREMIUM chico | N67: =P67*1.4 -> 1890 | P67: 1350 | R67: SUPER PANCHO 6 UN. | S67: =T67*1.485 -> 1568.16 | T67: 1056 | U67: Vainilla 28x 180 | V67: =W67*1.303 -> 0 | Y67: miel de kg | Z67: =AA67*1.32 -> 10560 | AA67: 8000
B68: alfajor glasi chico | C68: =M51 -> 0 | D68: =S72*C68 -> 0 | E68: =D130*C68 -> 0 | F68: estimad% | G68: =D112*0.33 -> 5299.8 | M68: Sandwich Escolar | N68: =P68*1.4 -> 700 | P68: 500 | U68: Vainilla x 2kg | V68: =W68*1.303 -> 10293.7 | W68: 7900 | Y68: crocante | Z68: =AA68*1.32 -> 7260 | AA68: 5500
B69: alfajr miel | C69: =N51 -> 0 | D69: =S73*C69 -> 0 | E69: =T73*C69 -> 0 | F69: gananci real | G69: =D112-F112 -> 16060 | M69: pebete | N69: =P69*1.4 -> 1400 | P69: 1000 | U69: Roscas x 1kg | V69: =W69*1.311 -> 7603.8 | W69: 5800 | Y69: premium | Z69: =AA69*1.321 -> 8454.4 | AA69: 6400
B70: alfajor chocola con mani | C70: =P51 -> 0 | D70: =S75*C70 -> 0 | E70: =D133*C70 -> 0 | F70: propio | G70: =D112-E112 -> 5060 | M70: *ALFAJORES* | R70: ANIS X 12 UND. | S70: 1850.8 | T70: 1997 | U70: Pepas x 2.5kg | V70: =W70*1.303 -> 10293.7 | W70: 7900 | Y70: glase x12 | Z70: =AA70*1.32 -> 3564 | AA70: 2700
B71: alfajor maise | C71: =O51 -> 0 | D71: =S74*C71 -> 0 | E71: =D132*C71 -> 0 | R71: ANIS X 24 | S71: =T71*1.46 -> 4850.12 | T71: 3322 | U71: fantasía x 2.5kg | V71: =W71*1.303 -> 10293.7 | W71: 7900
B72: pan dulce | C72: =Q51 -> 0 | D72: =S77*C72 -> 0 | M72: Miel/Maicena x20u | N72: =P72*1.46 -> 8030 | P72: 5500 | R72: alfajores glaciados x24un | S72: 6101.2 | T72: 4380
B73: del sol | D73: =SUM(D59:D72) -> 0 | E73: =SUM(E59:E72) -> 0 | M73: Miel/Maicena x12un. | N73: =P73*1.4 -> 3360 | P73: 2400 | R73: alfajores de miel x20un | S73: =T73*1.444 -> 9458.2 | T73: 6550
B74: surtidas 800g | C74: =Y51 -> 0 | D74: =V63*C74 -> 0 | E74: =W63*C74 -> 0 | M74: Glaseado x20un. | N74: =P74*1.46 -> 8030 | P74: 5500 | R74: alfajores Maizena x20un | S74: =T74*1.444 -> 7799.044 | T74: 5401
B75: surtidas400g | C75: =Z51 -> 0 | D75: =V64*C75 -> 0 | E75: =W64*C75 -> 0 | M75: Conitos de dulce de leche x12u. | N75: =P75*1.4 -> 5250 | P75: 3750 | R75: alfajor chocolate x 20un | S75: =T75*1.45 -> 10701 | T75: 7380
B76: miel 400g | C76: =AA51 -> 0 | D76: =V65*C76 -> 0 | E76: =W65*C76 -> 0 | M76: Chocolate con crocante de mani x20u. | N76: =P76*1.4 -> 10500 | P76: 7500 | R76: TOSTADAS POR 1KG | S76: 8000 | T76: 3600
B77: galleta 3kg limon | C77: =R51 -> 0 | D77: =V60*C77 -> 0 | E77: =J126*C77 -> 0 | R77: pan dulce | S77: 1500 | T77: 1300
B78: galleta 3kg coco | C78: =T51 -> 0 | D78: =V60*C78 -> 0 | E78: =W60*C78 -> 0 | M78: *POSTRES*
B79: galleta 3kg naraja | C79: =S51 -> 0 | D79: =V61*C79 -> 0 | E79: =J128*C79 -> 0
B80: rosca glaciada | C80: =U51 -> 0 | D80: =V69*C80 -> 0 | E80: =W69*C80 -> 0 | M80: Tiramisu | P80: 1300
B81: vainillas 2kg | C81: =V51 -> 0 | D81: =V63*C81 -> 0 | E81: =W68*C81 -> 0 | M81: Flan | N81: =P81*1.42 -> 2201 | P81: 1550
B82: pepap 2,5kg | C82: =W51 -> 0 | D82: =V64*C82 -> 0 | E82: =J131*C82 -> 0 | M82: Chocotorta | N82: =P82*1.42 -> 2201 | P82: 1550
B83: surtida 2.5kg | C83: =X51 -> 0 | D83: =V61*C83 -> 0 | E83: =W61*C83 -> 0 | M83: Ensalada de Fruta | N83: =P83*1.39 -> 1598.5 | P83: 1150
B84: lauti | D84: =SUM(D74:D83) -> 0 | E84: =SUM(E74:E83) -> 0 | M84: gelatina | N84: =P84*1.42 -> 1207 | P84: 850
B85: tiramisu | C85: =AL51 -> 0 | D85: =N80*C85 -> 0 | E85: =P80*C85 -> 0
B86: chocotorta | C86: =AK51 -> 0 | D86: =N82*C86 -> 0 | E86: =P82*C86 -> 0
B87: esalada de fruta | C87: =AM51 -> 0 | D87: =N83*C87 -> 0 | E87: =P83*C87 -> 0
B88: gelatina | C88: =AN51 -> 0 | D88: =N84*C88 -> 0 | E88: =P84*C88 -> 0
B89: flan | C89: =AO51 -> 0 | D89: =N81*C89 -> 0 | E89: =P81*C89 -> 0
B90: maisena | C90: =AF51 -> 1 | D90: =N72*C90 -> 8030 | E90: =P72*C90 -> 5500
B91: Miel | C91: =AH51 -> 0 | D91: =N72*C91 -> 0 | E91: =P72*C91 -> 0
B92: Glaseado x20un. | C92: =AG51 -> 1 | D92: =N74*C92 -> 8030 | E92: =P74*C92 -> 5500
B93: mixto /maise/miel | C93: =AJ51 -> 0 | D93: =N72*C93 -> 0 | E93: =P72*C93 -> 0
B94: sandwich salame gr | C94: =AE51 -> 0 | D94: =N76*C94 -> 0 | E94: =P72*C94 -> 0
B95: Sandwich de miga grande | C95: =AB51 -> 0 | D95: =N64*C95 -> 0 | E95: =P64*C95 -> 0
B96: Sandwich de miga chico | C96: =AC51 -> 0 | D96: =N65*C96 -> 0 | E96: =P65*C96 -> 0
B97: pebete de salame y queso | C97: =AD51 -> 0 | D97: =N69*C97 -> 0 | E97: =P69*C97 -> 0
B98: candela | D98: =SUM(D85:D97) -> 16060 | E98: =SUM(E85:E97) -> 11000
B99: premium | C99: =AP51 -> 0 | D99: =Z69*C99 -> 0 | E99: =AA69*C99 -> 0
B100: maisena | C100: =AQ51 -> 0 | D100: =Z60*C100 -> 0 | E100: =AA60*C100 -> 0
B101: miel | C101: =AR51 -> 0 | D101: =Z61*C101 -> 0 | E101: =P71*C101 -> 0
B102: glaciado | C102: =AS51 -> 0 | D102: =Z62*C102 -> 0 | E102: =AA61*C102 -> 0
B103: chocolate | C103: =AT51 -> 0 | D103: =Z68*C103 -> 0 | E103: =AA68*C103 -> 0
B104: combinado | C104: =AU51 -> 0 | D104: =Z63*C104 -> 0 | E104: =AA63*C104 -> 0
B105: alfajor frutal | C105: =AV51 -> 0 | D105: =Z65*C105 -> 0 | E105: =AA65*C105 -> 0
B106: miel 1kg | C106: =AW51 -> 0 | D106: =Z66*C106 -> 0 | E106: =AA67*C106 -> 0
B107: maisena 1kg | C107: =AX51 -> 0 | D107: =Z67*C107 -> 0 | E107: =AA66*C107 -> 0
B108: tartateleta cabsha | C108: =AY51 -> 0 | D108: =Z64*C108 -> 0 | E108: =AA64*C108 -> 0
D109: =Z69*C109 -> 0 | E109: =P79*C109 -> 0
D110: =Z70*C110 -> 0 | E110: =P80*C110 -> 0
D111: =SUM(D99:D110) -> 0 | E111: =SUM(E99:E110) -> 0
B112: total | D112: =SUM(D84,D73,D98,D111) -> 16060 | E112: =SUM(E111,E84,E73,E98) -> 11000 | F112: =SUM(F111,F98,F87,F73) -> 0
L116: -Ensalada de Frutas $900
L117: -Gelatina $600
L118: -Maní Saborizado 160gr $600
D119: actualisacion | H119: actualisacion | L119: berben
...

Sheet Hoja2
A1: cliente | B1: pancho | C1: haburguesa | D1: lactal blac | E1: lactal neg | F1: lomo | G1: pizza | H1: anis12 | I1: anis24 | J1: tostadas1kg | K1: alfajor glase | L1: alfajor miel | M1: alfajor maise
A2: semana 1 3/10-.04.24 | P2: pancho | Q2: =SUM(B3:B12) -> 29 | R2: =Hoja1!S62*Q2 -> 26521.95
A3: ameguino 255 | I3: 1 | J3: 1 | P3: haburgue | Q3: =SUM(C3:C12) -> 15 | R3: =Hoja1!S61*Q3 -> 13718.25
A4: peron 23 | B4: 2 | C4: 2 | D4: 3 | E4: 3 | P4: lactal blan | Q4: =SUM(D3:D12) -> 20 | R4: =Hoja1!S64*Q4 -> 25350.06
A5: camargo | B5: 10 | C5: 5 | D5: 2 | E5: 2 | P5: lactal negr | Q5: =SUM(E3:E12) -> 5 | R5: =Hoja1!S64*Q5 -> 6337.515
A6: paso abde y canto | K6: 1 | L6: 1 | P6: lomo | Q6: =SUM(F3:F12) -> 3 | R6: =Hoja1!S66*Q6 -> 5135.136
A7: flores | I7: 1 | P7: pizza | Q7: =SUM(G3:G12) -> 5 | R7: =Hoja1!S65*Q7 -> 10569
A8: peru lemon | I8: 1 | P8: aniz12 | Q8: =SUM(H3:H12) -> 2 | R8: =Hoja1!S70*Q8 -> 3701.6
A9: palacio y corre | B9: 5 | C9: 5 | D9: 5 | F9: 3 | G9: 5 | H9: 1 | P9: anis24 | Q9: =SUM(I3:I12) -> 3 | R9: =Hoja1!S71*Q9 -> 14550.36
A10: jasinto suare | B10: 3 | C10: 3 | D10: 3 | P10: totadas1kg | Q10: =SUM(J3:J12) -> 1 | R10: =Hoja1!S76*Q10 -> 8000 | S10: costo | T10: ganacia
A11: godoy | B11: 3 | D11: 2 | H11: 1 | K11: 1 | M11: 1 | P11: alfajor glasi | Q11: =SUM(K2:K12) -> 2 | R11: =Hoja1!S72*Q11 -> 12202.4 | T11: 32000
A12: champagña | B12: 6 | D12: 5 | P12: alfajr miel | Q12: =SUM(L2:L12) -> 1 | R12: =Hoja1!S73*Q12 -> 9458.2
A16: cliente | B16: pancho | C16: haburguesa | D16: lactal blac | E16: lactal neg | F16: lomo | G16: pizza | H16: anis12 | I16: anis24 | J16: tostadas1kg | K16: alfajor glase | L16: alfajor miel | M16: alfajor maise | N16: alfajor de chocolat
A17: semana 2 10/17 -.04.24 | O17: pancho | P17: =SUM(B18:B33) -> 45 | Q17: =Y45*P17 -> 0
A18: edu peleg | B18: 5 | C18: 5 | O18: haburgue | P18: =SUM(C18:C35) -> 35 | Q18: =Y44*P18 -> 0
A19: el negro | B19: 5 | C19: 5 | D19: 2 | E19: 2 | G19: 5 | I19: 1 | J19: 1 | O19: lactal blan | P19: =SUM(D18:D35) -> 28 | Q19: =Y47*P19 -> 0
A20: godoy | B20: 3 | D20: 3 | O20: lactal negr | P20: =SUM(E18:E35) -> 6 | Q20: =Y47*P20 -> 0
A21: paso abde y canto | D21: 3 | K21: 1 | N21: 1 | O21: lomo | P21: =SUM(F18:F35) -> 0 | Q21: =Y49*P21 -> 0
A22: visetichy italia | B22: 3 | C22: 3 | D22: 3 | E22: 2 | G22: 3 | O22: pizza | P22: =SUM(G18:G35) -> 16 | Q22: =Y48*P22 -> 0
A23: peru lemon | D23: 3 | I23: 2 | O23: aniz12 | P23: =SUM(H18:H35) -> 0 | Q23: =Y53*P23 -> 0
A24: palacio y corre | B24: 6 | C24: 4 | D24: 3 | G24: 6 | O24: anis24 | P24: =SUM(I18:I35) -> 3 | Q24: =Y54*P24 -> 0
A25: jasinto suare | B25: 2 | C25: 2 | D25: 3 | O25: totadas1kg | P25: =SUM(J18:J35) -> 1 | Q25: =Y59*P25 -> 0 | R25: costo | S25: ganacia
A26: cano serp | B26: 2 | D26: 2 | E26: 2 | O26: alfajor glasi | P26: =SUM(K17:K35) -> 1 | Q26: =Y55*P26 -> 0 | S26: =Q31-R31 -> 42212
A27: champagña | B27: 12 | C27: 9 | O27: alfajr miel | P27: =SUM(L17:L35) -> 1 | Q27: =Y56*P27 -> 0
A28: 1484 Marisa | B28: 5 | C28: 5 | D28: 3 | O28: alfajor chocola | P28: =SUM(N18:N50) -> 3 | Q28: =Y58*P28 -> 0
A29: ferrarri | B29: 2 | C29: 2 | D29: 3 | G29: 2 | O29: alfajor maise | P29: =SUM(M18:M35) -> 3 | Q29: =Y57*P29 -> 0
A30: ferrari 777
A31: ameguino255 | O31: total | Q31: 135000 | R31: 92788
A32: palacio y correa
A33: camargo
A34: igana sarmi | L34: 1 | M34: 3 | N34: 1
A38: cliente | B38: pancho | C38: haburguesa | D38: lactal blac | E38: lactal neg | F38: lomo | G38: pizza | H38: anis12 | I38: anis24 | J38: tostadas1kg | K38: alfajor glase | L38: alfajor miel | M38: alfajor maise | N38: alfajor de chocolat | O38: pan rallado de 5kg | Q38: pancho | R38: =SUM(B40:B55) -> 43 | S38: =Y53*R38 -> 0
A39: semana 2 17/ 2-.04.24 | Q39: haburgue | R39: =SUM(C40:C57) -> 24 | S39: =Y52*R39 -> 0
A40: edu peleg | D40: 4 | E40: 2 | Q40: lactal blan | R40: =SUM(D40:D57) -> 16 | S40: =Y55*R40 -> 0
A41: el negro | Q41: lactal negr | R41: =SUM(E40:E57) -> 2 | S41: =Y55*R41 -> 0
A42: godoy | Q42: lomo | R42: =SUM(F40:F57) -> 0 | S42: =Y57*R42 -> 0
A43: paso abde y canto | B43: 10 | C43: 10 | Q43: pizza | R43: =SUM(G40:G57) -> 3 | S43: =Y56*R43 -> 0
A44: visetichy italia | K44: 1 | N44: 1 | Q44: aniz12 | R44: =SUM(H40:H57) -> 0 | S44: =Y61*R44 -> 0
A45: peru lemon | Q45: anis24 | R45: =SUM(I40:I57) -> 2 | S45: =Y62*R45 -> 0
A46: palacio y corre | B46: 10 | C46: 6 | Q46: totadas1kg | R46: =SUM(J40:J57) -> 0 | S46: =Y67*R46 -> 0 | T46: costo | U46: ganacia
A47: jasinto suare | Q47: alfajor glasi | R47: =SUM(K39:K57) -> 1 | S47: =Y63*R47 -> 0 | U47: =S52-T52 -> 22186
A48: cano serp | B48: 3 | D48: 3 | Q48: alfajr miel | R48: =SUM(L39:L57) -> 0 | S48: =Y64*R48 -> 0
A49: champagña | B49: 12 | D49: 6 | Q49: alfajor chocola | R49: =SUM(N40:N58) -> 1 | S49: =Y66*R49 -> 0
A50: 1484 Marisa | Q50: alfajor maise | R50: =SUM(M40:M57) -> 0 | S50: =Y65*R50 -> 0
A51: ferrarri | D51: 3 | G51: 3 | I51: 1 | Q51: pan rallado5kg | R51: =SUM(O39:O58) -> 1 | S51: =Y59*R51 -> 0
A52: ferrari 777 | Q52: total | S52: 68500 | T52: 46314
A53: ameguino255 | I53: 1 | O53: 1
A54: palacio y correa
A55: camargo | B55: 8 | C55: 8
A56: igana sarmi
T57: primer semana | U57: 25000
U58: total
B59: mayo | U59: =SUM(U47,S26,T11,U57) -> 121398
A63: cliente | B63: pancho | C63: haburguesa | D63: lactal blac | E63: lactal neg | F63: lomo | G63: pizza | H63: anis12 | I63: anis24 | J63: tostadas1kg | K63: alfajor glase | L63: alfajor miel | M63: alfajor maise | N63: alfajor de chocolat | O63: pan rallado de 5kg
A64: semana 1 (1/ 5---8/05) 2024) | Q64: pancho | R64: =SUM(B65:B82) -> 31 | S64: =X78*R64 -> 0
A65: edu peleg | Q65: haburgue | R65: =SUM(C65:C82) -> 35 | S65: =X77*R65 -> 0
A66: el negro | G66: 5 | I66: 2 | Q66: lactal blan | R66: =SUM(D65:D82) -> 26 | S66: =X80*R66 -> 0
A67: godoy | Q67: lactal negr | R67: =SUM(E65:E82) -> 2 | S67: =X80*R67 -> 0
A68: paso abde y canto | B68: 5 | C68: 10 | D68: 5 | K68: 1 | L68: 1 | Q68: lomo | R68: =SUM(F65:F82) -> 0 | S68: =X82*R68 -> 0
A69: catamarca 1783 | I69: 1 | Q69: pizza | R69: =SUM(G65:G82) -> 13 | S69: =X81*R69 -> 0
A70: peru y visetichi | I70: 1 | Q70: aniz12 | R70: =SUM(H65:H82) -> 0 | S70: =X86*R70 -> 0
A71: Daniela abaya | L71: 1 | M71: 1 | Q71: anis24 | R71: =SUM(I65:I82) -> 7 | S71: =X87*R71 -> 0
A72: jasinto suare | B72: 3 | C72: 3 | D72: 3 | Q72: totadas1kg | R72: =SUM(J65:J82) -> 0 | S72: =X92*R72 -> 0 | T72: costo | U72: ganacia
A73: cano serp | B73: 3 | C73: 3 | Q73: alfajor glasi | R73: =SUM(K64:K82) -> 2 | S73: =X88*R73 -> 0 | U73: =S78-T78 -> 44085
A74: champagña | B74: 8 | C74: 6 | D74: 3 | Q74: alfajr miel | R74: =SUM(L64:L82) -> 3 | S74: =X89*R74 -> 0
A75: 1484 Marisa | D75: 3 | Q75: alfajor chocola | R75: =SUM(M65:M83) -> 1 | S75: =X91*R75 -> 0
A76: ferrarri | B76: 4 | C76: 3 | D76: 4 | G76: 2 | I76: 1 | Q76: alfajor maise | R76: =SUM(M65:M82) -> 1 | S76: =X90*R76 -> 0
A77: ferrari 777 | Q77: pan rallado5kg | S77: =X84*R77 -> 0
A78: flores | I78: 1 | Q78: total | S78: 127000 | T78: 82915
A79: palacio y correa | C79: 5 | D79: 4 | G79: 6
A80: juan b justo 255 | L80: 1 | N80: 1
A81: roca 829 | B81: 6 | C81: 3 | D81: 2
A82: hugo | B82: 2 | C82: 2 | D82: 2 | E82: 2 | I82: 1 | K82: 1
A87: distriubucion | B87: cliente | C87: pancho | D87: haburguesa | E87: lactal blac | F87: lactal neg | G87: lomo | H87: pizza | I87: anis12 | J87: anis24 | K87: tostadas1kg | L87: alfajor glase | M87: alfajor miel | N87: alfajor maise | O87: alfajor de chocolat | P87: pan rallado de 5kg
B88: semana 1 (1/ 5---8/05) 2024) | R88: pancho | S88: =SUM(C89:C106) -> 14 | T88: =Y102*S88 -> 0
A89: 14 | B89: ameguino255 | J89: 2 | R89: haburgue | S89: =SUM(D89:D106) -> 19 | T89: =Y101*S89 -> 0
A90: una rosquita 9 | B90: el negro | J90: 1 | M90: 1 | N90: 1 | R90: lactal blan | S90: =SUM(E89:E106) -> 13 | T90: =Y104*S90 -> 0
A91: 11 | B91: hugo | C91: 8 | D91: 8 | E91: 4 | L91: 5 | R91: lactal negr | S91: =SUM(F89:F106) -> 0 | T91: =Y104*S91 -> 0
A92: 6 | B92: paso abde y canto | D92: 5 | L92: 2 | M92: 2 | O92: 2 | R92: lomo | S92: =SUM(G89:G106) -> 0 | T92: =Y106*S92 -> 0
B93: catamarca 1783 | R93: pizza | S93: =SUM(H89:H106) -> 0 | T93: =Y105*S93 -> 0
A94: 8 | B94: peru y visetichi | J94: 1 | R94: aniz12 | S94: =SUM(I89:I106) -> 0 | T94: =Y110*S94 -> 0
B95: Daniela abaya | R95: anis24 | S95: =SUM(J89:J106) -> 7 | T95: =Y111*S95 -> 0
A96: 7 | B96: jasinto suare | C96: 3 | E96: 3 | R96: totadas1kg | S96: =SUM(K89:K106) -> 0 | T96: =Y116*S96 -> 0 | U96: costo | V96: ganacia
A97: 13 | B97: cano serp | D97: 3 | E97: 3 | R97: alfajor glasi | S97: =SUM(L88:L106) -> 10 | T97: =Y112*S97 -> 0 | V97: =T102-U102 -> 42815.55
A98: 12 | B98: champagña | C98: 3 | D98: 3 | E98: 3 | R98: alfajr miel | S98: =SUM(M88:M106) -> 6 | T98: =Y113*S98 -> 0
A99: 4 | B99: barcala 501 | J99: 1 | R99: alfajor chocola | S99: =SUM(O88:O106) -> 3 | T99: =Y115*S99 -> 0
B100: ferrarri | R100: alfajor maise | S100: =SUM(N89:N106) -> 3 | T100: =Y114*S100 -> 0
A101: 1 | B101: ferrari 777 | R101: pan rallado5kg | T101: =Y108*S101 -> 0
A102: 10 | B102: flores | J102: 1 | L102: 1 | R102: total | T102: 163702.55 | U102: 120887
B103: palacio y correa
A104: 5 | B104: juan b justo 255 | J104: 1 | M104: 1 | O104: 1
A105: 3 | B105: avellaneda y cani | L105: 1 | M105: 1 | N105: 1
A106: 2 | B106: las heras 1819 | L106: 1 | M106: 1 | N106: 1
A110: distriubucion | B110: cliente | C110: pancho | D110: haburguesa | E110: lactal blac | F110: lactal neg | G110: lomo | H110: pizza | I110: anis12 | J110: anis24 | K110: tostadas1kg | L110: alfajor glase | M110: alfajor miel | N110: alfajor maise | O110: alfajor de chocolat | P110: pan rallado de 5kg
B111: semana 1 (1/ 5---8/05) 2024) | R111: pancho | S111: =SUM(C112:C129) -> 61 | T111: =Y125*S111 -> 0
A112: vainilas 180gr una caja y un anillo | B112: ameguino255 | R112: haburgue | S112: =SUM(D112:D129) -> 37 | T112: =Y124*S112 -> 0
A113: 6 | B113: el negro | J113: 1 | R113: lactal blan | S113: =SUM(E112:E129) -> 16 | T113: =Y127*S113 -> 0
A114: 2 rosquitss(11) | B114: hugo | C114: 7 | F114: 4 | J114: 1 | R114: lactal negr | S114: =SUM(F112:F129) -> 5 | T114: =Y127*S114 -> 0
A115: 9 | B115: paso abde y canto | C115: 10 | D115: 10 | E115: 5 | R115: lomo | S115: =SUM(G112:G129) -> 2 | T115: =Y129*S115 -> 0
B116: lisandro y armada | R116: pizza | S116: =SUM(H112:H129) -> 2 | T116: =Y128*S116 -> 0
...

Sheet Hoja3
A3: cosas hacer | B3: $$$$$$ | C3: cosas a hacer para ya
A4: 16 hablar con comedor de lavalle del negro y publicidad en radio | C4: disco solido
A5: 21 deuda con supercanal | C5: ageriadora
A6: 22 deuda con tarjeta naranja
A7: cerrar con la empresa viento andino
A8: armar cillones
A9: terminar afip,empresa y facturar
A10: buscar mesa en la casa del Carlos ser posible baúl y calesita
A12: conseguir 1000 pesos que ponga la gente
A13: conseguir que pongo 10.00$
A14: conseguir que ponga100.00$
A15: conseguir q pongan1.000.000$
A16: cambiar cortina de niños y hacer la del pasillo
A17: hacer repisas flotantes
A18: , agulos en v y y madereas
... A24: conseguir mas de 10 comedores mendoza
A28: paragolpes | B28: 150000
A30: cubiertas x4 | B30: 100000 | C30: poner camara
A31: aceite y filtro | B31: 20000
A32: comba y alineasion | B32: 30000
A33: 15-9
A35: esmalte sintetico negro
A36: video juegos maximo
A37: conseguir cuenta dolar
A38: conseguir prestamos resposable incripto
A39: en chile
A40: juego de sabana 3
A41: juego de hoyas
A42: 1 jugo de sabana para 3 1 juego de ollas 1 jarra Una nootbook Un aire portátil 3 cortina 1 mini prim buena 1 proyector 1 Microfono 1 cierra bolsa 1 impresora 1 paraguas 1 Dron
A45: ganchos para lona
A46: 2 bolsas arena
A47: cañito
... A51: llevar un tornillo

Sheet Hoja9

Sheet Hoja7

Sheet Hoja8

Sheet Hoja4

Sheet Hoja5

Sheet Hoja6
